{"topicid": "MB179",
"topic": "care of Iditarod dogs",
"tweets":[
{"id":"306055477211590656","time":"Mon Feb 25 14:58:06 +0000 2013","name":"Debbie Duncan Dunn","screenname":"debbie3d","text":"Stand with ALDF against this cruel dog sled race! http://t.co/tT2w0gGTWk"},
{"id":"306062313948078081","time":"Mon Feb 25 15:25:16 +0000 2013","name":"clingtothewreckage","screenname":"arayah_mariah","text":"Animal Legal Defense Fund : Cruelty to Alaska’s Sled Dogs in the Iditarod http://t.co/gieDixtfix via @ALDF"},
{"id":"306107985694965760","time":"Mon Feb 25 18:26:45 +0000 2013","name":"Valerie PRINCE","screenname":"Riley650","text":"Animal Legal Defense Fund : Cruelty to Alaska’s Sled Dogs in the Iditarod http://t.co/nq3hCNlMll via @ALDF"},
{"id":"307934638674964480","time":"Sat Mar 02 19:25:13 +0000 2013","name":"Frontier Scientists","screenname":"FrontierSi","text":"One Mean Dance Partner: How Mother Nature Twirls the Sport of Dog Mushing http://t.co/LmLUMOec50 #Iditarod"},
{"id":"309225326674841600","time":"Wed Mar 06 08:53:57 +0000 2013","name":"Iditarod Insider","screenname":"IditarodInsider","text":"Burmeister stays in Takotna—Mackey intends to continue to Iditarod? http://t.co/zIJHiAfaQw"},
{"id":"309395342770724864","time":"Wed Mar 06 20:09:32 +0000 2013","name":"Team Marketing","screenname":"Team2Market","text":"Love of sport, not money, draws Iditarod mushers http://t.co/nGOXML0Gb5"},
{"id":"309446743957856257","time":"Wed Mar 06 23:33:47 +0000 2013","name":"Barbara Harris","screenname":"barbhars","text":"Iditarod Mushers Kill Thousands of Dogs: Dogs are hauling sleds behind them in the Iditarod Trail Sled Dog Rac... http://t.co/xrU5hp8cd4"},
{"id":"309963725492854784","time":"Fri Mar 08 09:48:05 +0000 2013","name":"Sammy Brace","screenname":"cleaninggirl","text":"Iditarod Mushers Kill Thousands of Dogs http://t.co/F948MiqgGL"},
{"id":"310001977528565760","time":"Fri Mar 08 12:20:05 +0000 2013","name":"Matter Moore Saints","screenname":"sm2198","text":"http://t.co/tQci8G6ZcA Iditarod Mushers Kill Thousands of Dogs"},
{"id":"311069063025676288","time":"Mon Mar 11 11:00:18 +0000 2013","name":"Alaska News","screenname":"Alaska_News_","text":"Women Inmates Care for Iditarod Dogs http://t.co/EsAZ9y9dNW"},
{"id":"311562128588935168","time":"Tue Mar 12 19:39:34 +0000 2013","name":"KNOM","screenname":"knom","text":"#Iditarod's Berkowitz in White Mountain: 'The last thing I’m going to do is drive my dogs hard the last 70 miles.' http://t.co/zRBv8F6Ghh"},
{"id":"312652811215204353","time":"Fri Mar 15 19:53:33 +0000 2013","name":"PetsPass","screenname":"petspass","text":"Iditarod Dog Found 7 Days After Disappearing From Team http://t.co/S1RVAXrUAI (via @ABC)"},
{"id":"312692099285913600","time":"Fri Mar 15 22:29:40 +0000 2013","name":"Dog Food Recipes","screenname":"Dog_Recipes","text":"Iditarod dog , missing 5 days, found alive: BIG LAKE, Alaska, March 15 (UPI) -- A sled dog that went missing d... http://t.co/QJOHOeMbNN"},
{"id":"312712479404875776","time":"Fri Mar 15 23:50:39 +0000 2013","name":"Diane Rich","screenname":"spokesdog","text":"Iditarod Dog Found 7 Days After Disappearing From Team http://t.co/sR53aeGyTm (via @ABC)"},
{"id":"312721111265710080","time":"Sat Mar 16 00:24:57 +0000 2013","name":"Malisha Serrano, DVM","screenname":"exoticsvet","text":"Iditarod Dog Found 7 Days After Disappearing From Team | ABC News Blogs - Yahoo! http://t.co/nriV3kH40I via @YahooNews"},
{"id":"312902712062799873","time":"Sat Mar 16 12:26:34 +0000 2013","name":"Shirley May Johnson","screenname":"shirleybird2","text":"Iditarod dog Dorado found dead in snow in town of Unalakeet, Alaska - News | FOX Sports on MSN http://t.co/2EVyZvm3i4 via @FoxSports"},
{"id":"313043577762631681","time":"Sat Mar 16 21:46:19 +0000 2013","name":"Leonie Doyle","screenname":"leoniedoyle","text":"In Alaska, an Iditarod dog that can't keep up gets 'dropped', dies in snow. First since 2009 http://t.co/KM1qnMzeem via @AKbirder"},
{"id":"313072908526313472","time":"Sat Mar 16 23:42:52 +0000 2013","name":"Richard Wile","screenname":"richardwile","text":"#latest #news Iditarod Dog Dies In Unalakleet, Alaska After Being Dropped Race: ANCHORAGE, Alaska — Officials ... http://t.co/ueFtclJF55"},
{"id":"313083528504033281","time":"Sun Mar 17 00:25:04 +0000 2013","name":"Kennedy Kaito Conan","screenname":"JwcKennedy","text":"Iditarod Dog Dies In Unalakleet, Alaska After Being Dropped Race http://t.co/V1uHKPhonp"},
{"id":"313085994733809664","time":"Sun Mar 17 00:34:52 +0000 2013","name":"Traveloinfo","screenname":"Traveloinfo","text":"Iditarod Dog Dies In Unalakleet, Alaska After Being Dropped Race: ANCHORAGE, Alaska — Officials say a dog that d... http://t.co/csNI9AWGGb"},
{"id":"313116357329821696","time":"Sun Mar 17 02:35:31 +0000 2013","name":"Ahmed Nassar","screenname":"4EE4","text":"Iditarod dog dies after being buried in snow: A dog left behind at a checkpoint in Alaska was smothered by win... http://t.co/5wM23GXeV1"},
{"id":"313120471937855489","time":"Sun Mar 17 02:51:52 +0000 2013","name":"Shiit happens ☇♥ (._","screenname":"Thug_Amin","text":"Iditarod dog dies after being buried in snow: A dog left behind at a checkpoint in Alaska was smothe... http://t.co/s47iVida8O #thuggish"},
{"id":"313131624562823168","time":"Sun Mar 17 03:36:11 +0000 2013","name":"Carrie Bathelely","screenname":"CarrieBathelely","text":"Iditarod dog died of asphyxiation, buried in snow: Race officials disclosed the results of the necropsy for 5-year-old Dorado, who wa..."},
{"id":"313198167199997952","time":"Sun Mar 17 08:00:36 +0000 2013","name":"Noma","screenname":"zlore05p","text":"Iditarod dog dies after being buried in snow http://t.co/cTaSYZKFpx"},
{"id":"313231377724219392","time":"Sun Mar 17 10:12:34 +0000 2013","name":"Jovana Weltch","screenname":"JovanaWeltch","text":"Iditarod dog died of asphyxiation, buried in snow"},
{"id":"313752834556452864","time":"Mon Mar 18 20:44:39 +0000 2013","name":"West Suburban Dog","screenname":"WestSuburbanDog","text":"Finally, a Happy Ending at Iditarod: A Lost Dog Is Found After 7 Days  via @Dogster http://t.co/gRKDtB9VNP"},
{"id":"314149997413277696","time":"Tue Mar 19 23:02:50 +0000 2013","name":"vadson ferreira","screenname":"vadson27","text":"Activist group seeks charges in Iditarod dog death http://t.co/eJYpaOWBnB"},
{"id":"314150320370483201","time":"Tue Mar 19 23:04:07 +0000 2013","name":"Wasilla Gorilla","screenname":"Wasilla_Gorilla","text":"(AK Disp News Featu) PETA urges Nome DA to file cruelty charges over Iditarod dog's death: PETA urges Nome... http://t.co/TTNR6FF3fA #AK"},
{"id":"314163100397993985","time":"Tue Mar 19 23:54:54 +0000 2013","name":"Inno3D","screenname":"Inno3D","text":"Activist group seeks charges in Iditarod dog death: PETA has long criticized the 1,000-mile Alaskan sled race ... http://t.co/2pEQbAzXy2"},
{"id":"314173330322239489","time":"Wed Mar 20 00:35:33 +0000 2013","name":"Berkley Bear","screenname":"BerkleyBearNews","text":"Activist group seeks charges in Iditarod dog death http://t.co/DxjUViw0fo"},
{"id":"314246432850849792","time":"Wed Mar 20 05:26:02 +0000 2013","name":"dixē.flatlin3","screenname":"dixeflatlin3","text":"#FirstWorldProblems #PETA seeks criminal charges in death of #dog dropped from #Iditarod Trail Sled Dog #Race: http://t.co/5anpgWazOy"},
{"id":"314250530660708352","time":"Wed Mar 20 05:42:19 +0000 2013","name":"David Anderson","screenname":"worldsnews3","text":"Criminal charges sought in Iditarod dog death http://t.co/legrbHuEuI"},
{"id":"314250530664882176","time":"Wed Mar 20 05:42:19 +0000 2013","name":"David Moore","screenname":"worldsnews2","text":"Criminal charges sought in Iditarod dog death http://t.co/Gza0uQm5PV"},
{"id":"314312556040818688","time":"Wed Mar 20 09:48:47 +0000 2013","name":"Mister TEE","screenname":"Tofbalzy1","text":"PETA pushes for criminal charges in Iditarod dog death:  http://t.co/C3aOBbhkKa"},
{"id":"314313193583419392","time":"Wed Mar 20 09:51:19 +0000 2013","name":"news com","screenname":"numbersonenews","text":"PETA pushes for criminal charges in Iditarod dog death http://t.co/HsG2HlG2pf"},
{"id":"314405992567808000","time":"Wed Mar 20 16:00:04 +0000 2013","name":"Pablo Galgo","screenname":"pablogalgo","text":"Iditarod Tragedy: Dog Suffocates Under Snow—Will Justice Be Served?: In light of the death of Dorado—a 5-year-... http://t.co/j4gZDmz1eM"},
{"id":"314477442519666689","time":"Wed Mar 20 20:43:59 +0000 2013","name":"Jen N' Joni","screenname":"twowisegals","text":"SO Tragic! Iditarod #dog dies after frigid night outside; charges are urged  http://t.co/DSaANi5wqH"},
{"id":"314503413645848576","time":"Wed Mar 20 22:27:11 +0000 2013","name":"Booker Owens","screenname":"xiafrq","text":"Iditarod dog dies after being buried by snow"},
{"id":"314719361581608960","time":"Thu Mar 21 12:45:17 +0000 2013","name":"Aaliyah Addison","screenname":"AalAaliyah","text":"Iditarod plans changes after sled dog death: Changes are planned for Alaska's Iditarod Trail Sled Dog Race fol... http://t.co/siqvcTgpmb"},
{"id":"314720372417241089","time":"Thu Mar 21 12:49:18 +0000 2013","name":"Atilio Gonzalez","screenname":"atilgon","text":"Iditarod plans changes after sled dog death http://t.co/LBGjsF9gcK"},
{"id":"314904967918006273","time":"Fri Mar 22 01:02:49 +0000 2013","name":"Alaska Online","screenname":"alaskaonline","text":"Iditarod plans changes after sled dog death: ANCHORAGE — Changes are planned for Alaska’s Iditarod Trail Sled Dog... http://t.co/Nji4c8TwU4"},
{"id":"315020286128971777","time":"Fri Mar 22 08:41:03 +0000 2013","name":"lennyesq","screenname":"lennyesq","text":"Iditarod musher whose dog died to sue PETA unless organization retracts comments blaming the musher http://t.co/fWc70up5Kn via @breakingnews"},
{"id":"315041433813938176","time":"Fri Mar 22 10:05:05 +0000 2013","name":"petcondition","screenname":"petcondition","text":"Women Inmates Care for Iditarod Dogs http://t.co/R09Vr9YkI2"},
{"id":"315126687232847873","time":"Fri Mar 22 15:43:51 +0000 2013","name":"CharlieThePooch","screenname":"CharlieThePooch","text":"It's About Time! Iditarod Plans Changes After Sled Dog's Death http://t.co/hSggyUJrsO"},
{"id":"317961764098695168","time":"Sat Mar 30 11:29:26 +0000 2013","name":"Kelly Brown","screenname":"MsKellyBBrown","text":"Iditarod dog awaiting transport to Anchorage after dropping from race dies in ...: The 5-year-old dog named Do... http://t.co/Y8XEtcOfza"},
{"id":"318285992178089984","time":"Sun Mar 31 08:57:48 +0000 2013","name":"Andrea K.","screenname":"Emmylou0403","text":"Iditarod Sled Dog Death Will Lead To Changes, Race Organizers Say http://t.co/1p3A8HOeHh via @HuffPostGreen"}
]}