{"topicid": "MB090",
"topic": "anti-bullying",
"tweets":[
{"id":"29420719704117248","time":"Mon Jan 24 06:10:20 +0000 2011","name":"Tony Bartoli","screenname":"stopbullyingtb","text":"School Bullying Prevention Tip #4 - Take the time to Stand out on the issue, it's just that important. #moms #dads #teachers"},
{"id":"29544990346575872","time":"Mon Jan 24 14:24:09 +0000 2011","name":"Donna McCabe","screenname":"Donna_McCabe","text":"New Irish mob app. lets parents spy on kids in name of preventing cyberbullying. Spying is not the answer. http://tinyurl.com/5wza6x9"},
{"id":"29591941876285440","time":"Mon Jan 24 17:30:43 +0000 2011","name":"NMSA","screenname":"NMSAnews","text":"End name calling. Participate in No Name-Calling Week, January 24-28, 2011. http://bit.ly/hyCtLb"},
{"id":"29632092828602368","time":"Mon Jan 24 20:10:16 +0000 2011","name":"Extreme Pizza KevinS","screenname":"extremepizzalj","text":"The Golden Rule... How would want to be treated?  La Jolla High Takes a Stand Against Bullying - http://patch.com/A-d0Y4"},
{"id":"29732191118295040","time":"Tue Jan 25 02:48:01 +0000 2011","name":"My Baby Clothes","screenname":"MyBabyClothes","text":"book guide from child therapist for No-Name Calling week - http://bit.ly/g3fWEp #parenting #stopbullying @parentella @MomDiaries"},
{"id":"29910591149707264","time":"Tue Jan 25 14:36:55 +0000 2011","name":"DanceTheatreTN","screenname":"DanceTheatreTN","text":"Another #UglyDuckling day at the #ballet for us here at DTT as we go on our 2nd day of our #AntiBullying outreach program"},
{"id":"29913987764195328","time":"Tue Jan 25 14:50:25 +0000 2011","name":"GATE America","screenname":"gateamerica","text":"Bullying, Dating Violence, Prescription Drug Abuse, are just a few of the 40 lesson that we offer for more info go to http://bit.ly/i69r4C"},
{"id":"30006118478512129","time":"Tue Jan 25 20:56:30 +0000 2011","name":"Boys and Girls Clubs","screenname":"OKboysandgirls","text":"Wowser...are Pink Shirt Anti-Bullying T-shirts are FLYING out the doors! Order your's today before they're all gone!"},
{"id":"30007189145919488","time":"Tue Jan 25 21:00:46 +0000 2011","name":"CAPS","screenname":"bullyprevention","text":"We invite you to read CAPS' new blog CONNECTIONS and join the dialogue to stop bullying http://capsbullypreventioncenter.com/"},
{"id":"30185572010033152","time":"Wed Jan 26 08:49:35 +0000 2011","name":"Elaine Clark","screenname":"cheapaccounting","text":"Final post in our series on Bullying in the work place - How a business should handle bullying http://bit.ly/eMb0Cy"},
{"id":"30194530934333441","time":"Wed Jan 26 09:25:11 +0000 2011","name":"ABC7 Eyewitness News","screenname":"abc7","text":"Some parents feel helpless to stop bullies from picking on kids. Here are tips on “bully-proofing” your child http://bit.ly/fTlH32"},
{"id":"30294939292139520","time":"Wed Jan 26 16:04:11 +0000 2011","name":"Nathan Triplett","screenname":"NathanTriplett","text":"is encouraging members of the Michigan House to cosponsor Representative Mark Meadows reintroduction of anti-bullying legislation."},
{"id":"30297740420321280","time":"Wed Jan 26 16:15:18 +0000 2011","name":"Jos M. Kubicek, CMC","screenname":"GLCompany","text":"Standing up to bully “employees” and leading by example.  Excellent Article: http://bit.ly/dJtC3d via @artpetty"},
{"id":"30344501788672001","time":"Wed Jan 26 19:21:07 +0000 2011","name":"Bullying Matters","screenname":"BullyingMatters","text":"Want more help or advice to do with bullying? Then check out or website: www.bullyingmatters.moonfruit.com"},
{"id":"30587022007603200","time":"Thu Jan 27 11:24:48 +0000 2011","name":"Autism Network","screenname":"autismnetwrk","text":"News: Workshop: Preventing Bullying - Positive Behavior Support In Schools http://ow.ly/1b3fNW"},
{"id":"30626856424177664","time":"Thu Jan 27 14:03:06 +0000 2011","name":"Denver Local News","screenname":"denverlocal","text":"Brentwood students give bullying the boot - http://fwix.com/a/27_9465561f83"},
{"id":"30677307916029953","time":"Thu Jan 27 17:23:34 +0000 2011","name":"Desirae Storm","screenname":"AffiliateGal89","text":"#Education School Bullies, Bullying, self-defense, self-defence, martial arts http://martialarts808.com/Bullying/"},
{"id":"30811039540969472","time":"Fri Jan 28 02:14:58 +0000 2011","name":"Desirae Storm","screenname":"AffiliateGal89","text":"#Children When Bullies Attack with Affiliate Program http://martialarts808.com/Bullying/BulliesPdc.htm"},
{"id":"30909554422194177","time":"Fri Jan 28 08:46:26 +0000 2011","name":"eLobbyist PA","screenname":"eLobbyistPA","text":"HB271 [NEW] Providing for the offense of bullying. http://bitly.com/5wMRS0"},
{"id":"31010364237815808","time":"Fri Jan 28 15:27:01 +0000 2011","name":"silasgrant","screenname":"silasgrant","text":"Im looking forward to doing an Anti-Bullying PSA this evening. Thanks to @CommunPR"},
{"id":"31052254433775617","time":"Fri Jan 28 18:13:29 +0000 2011","name":"AfterHoursPediatrics","screenname":"AHPediatrics","text":"N.J. teen creates anti-bullying school program http://sbne.ws/r/6CX2"},
{"id":"31058594338181121","time":"Fri Jan 28 18:38:40 +0000 2011","name":"Lori Lite","screenname":"StressFreeKids","text":"@relaxkids Bullies Sense Anxiety. http://bit.ly/ehB4Vw Relaxation techniques so important."},
{"id":"31081681955848193","time":"Fri Jan 28 20:10:25 +0000 2011","name":"Matt Gavin","screenname":"MattGavin","text":"MA Anti-Bullying PSA produced by @sandwichtv http://t.co/OiC8xyz via @youtube"},
{"id":"31180699922866177","time":"Sat Jan 29 02:43:52 +0000 2011","name":"Shane Skillen","screenname":"ShaneSkillen","text":"Audit of Blackfoot schools' anti-bullying policies released: “What we're suggesting is that, in addition to anti... http://bit.ly/g77C9v"},
{"id":"31198962056695809","time":"Sat Jan 29 03:56:26 +0000 2011","name":"Aviva","screenname":"FunandFunction","text":"Interesting perspective from the Mom of a reformed bully.  What do you think?  Would you tell a parent of a child... http://fb.me/PadVbCNs"},
{"id":"31214698540048384","time":"Sat Jan 29 04:58:58 +0000 2011","name":"S. Johnson","screenname":"StopBullying9","text":"http://stopbullyinghelp.blogspot.com/ laws about bullying"},
{"id":"31368638988558337","time":"Sat Jan 29 15:10:40 +0000 2011","name":"Flaura Winston MDPhD","screenname":"safetymd","text":"WAY TO GO, ASHLEY!  NJ teen launches anti-bullying program http://t.co/JCZB3zz"},
{"id":"31536020499468289","time":"Sun Jan 30 02:15:47 +0000 2011","name":"The SISFI Network","screenname":"SISFINetwork","text":"SISFI's Abuse/Bullying & Suicide Prevention Bus Tour/Road Show T-Shirt design competition will be launched in Jan 30th. Can YOU design it?"},
{"id":"31700382858092544","time":"Sun Jan 30 13:08:54 +0000 2011","name":"Shane Skillen","screenname":"ShaneSkillen","text":"Capital District works to combat bullying problem - troyrecord.com: ... fights last year at Doyle Middle School ... http://bit.ly/fOS9JK"},
{"id":"31729824913424384","time":"Sun Jan 30 15:05:54 +0000 2011","name":"Lori Lite","screenname":"StressFreeKids","text":"@60secondparent I really loved your sense of humor article. It helps in Bully Proofing children. http://bit.ly/ehB4Vw -&gt;though u might like"},
{"id":"31885777986129920","time":"Mon Jan 31 01:25:36 +0000 2011","name":"cristino herrera ","screenname":"ya433","text":"I favorited a YouTube video -- Anti-Bullying ad http://youtu.be/nWJut7KQhI4?a"},
{"id":"31919063512915968","time":"Mon Jan 31 03:37:52 +0000 2011","name":"Sam","screenname":"StopBullyNow","text":"Stepping Stones Fights Bullying: Just Ask Arianna Bailey, a Brien McMahon High School senior who said bullies ha... http://bit.ly/he7sKx"},
{"id":"32062413691944960","time":"Mon Jan 31 13:07:29 +0000 2011","name":"Jenny Smith","screenname":"hargel411","text":"Jan. 31: Cyberbullying, Water Quality and Kindergarten Registration: Give Yourself The Gift of Health at the Smi... http://bit.ly/h9jHvy"},
{"id":"32133833901998080","time":"Mon Jan 31 17:51:17 +0000 2011","name":"Potomac Kempo","screenname":"PotomacKempo","text":"I favorited a YouTube video -- Grandmaster Steve DeMasco Takes a Stand Against Bullying http://youtu.be/upVK1dNw33A?a"},
{"id":"32174153079455744","time":"Mon Jan 31 20:31:30 +0000 2011","name":"bailey bosler","screenname":"baileybosler23","text":"ASFL student's comic books cover serious topics: Kobe's book on bullying came from that class, but he continues ... http://bit.ly/iibOHQ"},
{"id":"32203718459916289","time":"Mon Jan 31 22:28:59 +0000 2011","name":"Ron Graham","screenname":"rongraham1","text":"The bully-stake-out Daily is out! http://bit.ly/e5cgUx ▸ Top stories today by @bullyingedu @bullybust @mommylok"},
{"id":"32206510473871360","time":"Mon Jan 31 22:40:05 +0000 2011","name":"Charity Greetings ","screenname":"cgreetingsnews","text":"#Greetingcards supporting @bullyinguk http://cardshop.bullying.co.uk - Just launched, check us out :-)"},
{"id":"32348602307190784","time":"Tue Feb 01 08:04:42 +0000 2011","name":"Bryan Chapman","screenname":"DiscrimLawyer","text":"By penalty of law: “I am biased in favor of bullying in schools and in the workplace becoming an issue in both t... http://bit.ly/i5xo4p"},
{"id":"32516535801090048","time":"Tue Feb 01 19:12:00 +0000 2011","name":"Ten Thirty-One Pic","screenname":"TenThirtyOnePic","text":"New resources 4 #teachers & #parents 4 #film about causes & consequences of #schoolviolence #bullying at http://TheOnlyWayTeaches.com"},
{"id":"32592002486902784","time":"Wed Feb 02 00:11:53 +0000 2011","name":"SafeSchoolsActionNet","screenname":"SafeSchoolsNow","text":"7 teens arrested in kidnapping, assault in Bullying Case http://t.co/dk7Ej3k / #safeschools #k12 #lgbt"},
{"id":"32627792780726273","time":"Wed Feb 02 02:34:06 +0000 2011","name":"Oakville News","screenname":"OakvilleNews","text":"St. Andrew and St. Michael Schools Hold Second Annual Bullying Awareness Conference http://www.oakville.com/n/i84"},
{"id":"32898416442867712","time":"Wed Feb 02 20:29:28 +0000 2011","name":"Vino Moda","screenname":"VinoModa","text":"Jennifer Aniston Cures Perez Hilton Of His Bullying Ways http://goo.gl/fb/8l7zz"},
{"id":"33099156532760576","time":"Thu Feb 03 09:47:08 +0000 2011","name":"Desirae Storm","screenname":"AffiliateGal89","text":"#Children When Bullies Attack with Affiliate Program http://martialarts808.com/Bullying/BulliesPdc.htm"},
{"id":"33171377213145088","time":"Thu Feb 03 14:34:07 +0000 2011","name":"Our Kids Media","screenname":"ourkidsnet","text":"Today on the blog: Is a new show on MTV glorifying bullying? An anti-bullying advocate speaks out http://ow.ly/3PyOI"},
{"id":"33226832933289984","time":"Thu Feb 03 18:14:28 +0000 2011","name":"Ivka Koleva","screenname":"skitnica0808","text":"Jennifer Aniston Confronted Perez Hilton and Inspired Him to Stop Bullying (VIDEO) http://aol.it/eUhC1n"},
{"id":"33236204107341825","time":"Thu Feb 03 18:51:43 +0000 2011","name":"justin delage","screenname":"meraboire","text":"Time to take the 'cyber' out of cyberbullying *http://bit.ly/ewxWdJ"},
{"id":"33238710594187264","time":"Thu Feb 03 19:01:40 +0000 2011","name":"Steve Hoffman","screenname":"goodnoteDJ","text":"Thanks, Wash. Post, for defending a local alternative paper against vexatious bullying by Dan Snyder http://wapo.st/hbj6g1"},
{"id":"33250008883007488","time":"Thu Feb 03 19:46:34 +0000 2011","name":"champ123","screenname":"champ1000","text":"National Attention Of Technological Harassment-Cyber Bullying http://j.mp/ibFPGG via @AddToAny"},
{"id":"33262971782176768","time":"Thu Feb 03 20:38:05 +0000 2011","name":"person net au","screenname":"personnetau","text":"Time to take the 'cyber' out of cyberbullying http://bit.ly/fpaaj6"},
{"id":"33320872324374529","time":"Fri Feb 04 00:28:09 +0000 2011","name":"Mίƈħaει FίτzĢεraιɖ ©","screenname":"MikeeFitz","text":"Just saw the video of @DeseanJackson10 @CenterStage67 and @toddherremans supporting that 13 yr old boy who was bullied. Pretty cool stuff!!"},
{"id":"33369992103723008","time":"Fri Feb 04 03:43:20 +0000 2011","name":"Bullying UK","screenname":"bullyinguk","text":"USER CREATED: Anti-Bullying Poster by Jaden 52847 Posters Created http://buk.cc/e0t4rL"},
{"id":"33373628129087490","time":"Fri Feb 04 03:57:47 +0000 2011","name":"Jennifer Amber","screenname":"OneWandering","text":"Good on #JenniferAnniston for speaking up about bullying! (And for being a good sport): http://www.youtube.com/watch?v=vUF8TJXSzKg"},
{"id":"33373801777467392","time":"Fri Feb 04 03:58:29 +0000 2011","name":"mark vinnicombe","screenname":"freelanceprofit","text":"Parents, students, educators get tips on preventing bullying: Ten district schools organized the event that was ... http://bit.ly/gDIOUH"},
{"id":"33383797051359232","time":"Fri Feb 04 04:38:12 +0000 2011","name":"Rob L","screenname":"ArtOfTheComment","text":"Shouts to DeSean Jackson, sticking up for that bullied kid from PA."},
{"id":"33496291401007105","time":"Fri Feb 04 12:05:12 +0000 2011","name":"The MidEast Journal","screenname":"MidEastJournal","text":"Hurriyet: Turkish center helps workplace bullying victims return to job market:  http://bit.ly/eHHs8D"},
{"id":"33538179063754752","time":"Fri Feb 04 14:51:39 +0000 2011","name":"Michelle Carrier","screenname":"Bestmotherof3","text":"Me too@thomaslynn: I'll be sporting mine will you? RT @chelsea_mac1: Wednesday, February 23 is Anti-Bullying Day http://www.pinkshirtday.ca/"},
{"id":"33560398212890624","time":"Fri Feb 04 16:19:57 +0000 2011","name":"alan sonntag","screenname":"alsonn17","text":"@DeseanJackson10 what you did for Nasin  yesterday was awesome, thanks for looking out for him and speaking out against bullying."},
{"id":"33653130809974784","time":"Fri Feb 04 22:28:26 +0000 2011","name":"Ron Graham","screenname":"rongraham1","text":"The bully-stake-out Daily is out! http://bit.ly/e5cgUx ▸ Top stories today via @kidsareheroes @takebackpride"},
{"id":"33689444728963072","time":"Sat Feb 05 00:52:44 +0000 2011","name":"Affrodite","screenname":"affrodite","text":"“ifelicious :@InTheLife addresses #LGBT #bullying, organizations Homecoming Project & Yes Project. http://wp.me/pr5fT-2dy must watch! #lgbt"},
{"id":"33700450280669185","time":"Sat Feb 05 01:36:28 +0000 2011","name":"M Katherine Pedroza","screenname":"DreamLikeMe","text":"@SheridanMae25 no, it has great tips on what to do if you're being bullied from experts, please read it :)"},
{"id":"33703316437340160","time":"Sat Feb 05 01:47:51 +0000 2011","name":"Keyah","screenname":"varietyofpretty","text":"Video: DeSean Jackson DeSean (Eagles) Surprises Bullied Teen, Who Was Hung Up On A Fence, On The View! http://t.co/is1lI2m via @worldstar"},
{"id":"33734396930564096","time":"Sat Feb 05 03:51:21 +0000 2011","name":"Alexa Fontanella","screenname":"Lexa_BeyJay4eva","text":"@DeseanJackson10 it was gr8 what u did for Nadin...bullying needs 2 b stopped and more stars and athletes need to make people aware..THANKS!"},
{"id":"33920448970358785","time":"Sat Feb 05 16:10:39 +0000 2011","name":"Spotsy Martial Arts","screenname":"FredericksbrgMA","text":"From Child Safety Fredericksburg: Three Keys to Preventing a Bully Encounter http://t.co/TKOH0EZ via @AddThis"},
{"id":"33986023419547648","time":"Sat Feb 05 20:31:14 +0000 2011","name":"Lori Lite","screenname":"StressFreeKids","text":"@workingmothers Tips to Bully Proof Kids! http://bit.ly/ehB4Vw"},
{"id":"34100187647451136","time":"Sun Feb 06 04:04:52 +0000 2011","name":"BulliesOut","screenname":"BulliesOut","text":"An Antibullying Agenda That’s Not So Hidden: Tolerance: Readers respond to article about an effort to stop bull... http://nyti.ms/eQYjqR"},
{"id":"34102550642823168","time":"Sun Feb 06 04:14:16 +0000 2011","name":"Chenay Hudson","screenname":"ilalalalalovejb","text":"my best friends sister commited suicide because of cyber bullying,its the worst.please sign this and end the hate http://twitition.com/8yojl"},
{"id":"34429524359778304","time":"Mon Feb 07 01:53:32 +0000 2011","name":"wanlop","screenname":"24Shopaholic","text":"Stop The Bull - A Parent & Educators Guide to Cyber Bullying: Facebook, twitter, and the likes, are changing lif... http://bit.ly/gyhs4q"},
{"id":"34479462124888064","time":"Mon Feb 07 05:11:59 +0000 2011","name":"Tony Bartoli","screenname":"stopbullyingtb","text":"#moms #dads Bullying Awareness  & Prevention Tip of the day&gt; Get students to LEARN comebacks to not become targets 4 Bullies. #kids #health"},
{"id":"34599992903606274","time":"Mon Feb 07 13:10:55 +0000 2011","name":"Mandy-Jane Clarke","screenname":"St0pBully","text":"Autism Awareness Month: Education key to stop the bullies - http://tinyurl.com/6k7oh8m"},
{"id":"34665932534063104","time":"Mon Feb 07 17:32:57 +0000 2011","name":"Debbie Scaduto","screenname":"debbiescaduto","text":"@GMA Recording artists Michael & Marisa help bullying victims with their Amazing new song & video, “The Same” http://goo.gl/MEcXa"},
{"id":"34709271165800448","time":"Mon Feb 07 20:25:09 +0000 2011","name":"newsandshopping","screenname":"newsandshopping","text":"Charities slam Asbo replacements: New plans to tackle anti-social behaviour, which will repla... http://bbc.in/i5fYBc http://ow.ly/3KSQn"},
{"id":"34921291089711104","time":"Tue Feb 08 10:27:39 +0000 2011","name":"Honolulu Local","screenname":"honolululocal","text":"Parents, Prosecutor support anti-bullying bills - http://fwix.com/a/29_3e5d63c788"}
]}